stag/__init__.py
stag/args.py
stag/cache.py
stag/config.py
stag/ecs.py
stag/exceptions.py
stag/plugins/__init__.py
stag/plugins/_helpers.py
stag/plugins/adoc/__init__.py
stag/plugins/adoc/adoc.py
stag/plugins/macros/__init__.py
stag/plugins/macros/macros.py
stag/plugins/macros/stag.html
stag/plugins/md/__init__.py
stag/plugins/md/md.py
stag/plugins/raw_markup/__init__.py
stag/plugins/raw_markup/raw_markup.py
stag/plugins/taxonomies/__init__.py
stag/plugins/taxonomies/taxonomies.py
stag/reading.py
stag/server.py
stag/server_helpers.py
stag/signals.py
stag/site.py
stag/stag.py
stag/utils.py
stag/writers/__init__.py
stag/writers/copy.py
stag/writers/jinja.py
stag/writers/template_functions.py
stag/writing.py
stag_ssg-0.12.1.dist-info/LICENSE
stag_ssg-0.12.1.dist-info/METADATA
stag_ssg-0.12.1.dist-info/WHEEL
stag_ssg-0.12.1.dist-info/entry_points.txt
stag_ssg-0.12.1.dist-info/RECORD
