Metadata-Version: 2.3
Name: stag-ssg
Version: 0.12.1
Summary: Deadly simple static site generator
License: GPL-3.0-only
Keywords: static site generator
Author: Michal Goral
Author-email: dev@goral.net.pl
Requires-Python: >=3.8,<4.0
Classifier: Development Status :: 5 - Production/Stable
Classifier: Environment :: Console
Classifier: Intended Audience :: Developers
Classifier: Intended Audience :: End Users/Desktop
Classifier: Intended Audience :: Information Technology
Classifier: License :: OSI Approved :: GNU General Public License v3 (GPLv3)
Classifier: License :: OSI Approved :: GNU General Public License v3 or later (GPLv3+)
Classifier: Natural Language :: English
Classifier: Operating System :: POSIX
Classifier: Programming Language :: Python :: 3
Classifier: Programming Language :: Python :: 3.8
Classifier: Programming Language :: Python :: 3.9
Classifier: Programming Language :: Python :: 3.10
Classifier: Programming Language :: Python :: 3.11
Classifier: Programming Language :: Python :: 3.12
Classifier: Programming Language :: Python :: 3.13
Classifier: Topic :: Internet :: WWW/HTTP :: Site Management
Classifier: Topic :: Utilities
Requires-Dist: attrs (>=21,<22)
Requires-Dist: beautifulsoup4 (>=4.13,<5.0)
Requires-Dist: importlib-metadata (>=4.0,<5.0) ; python_version < "3.8"
Requires-Dist: jinja2 (>=3,<4)
Requires-Dist: lxml (>=5.3,<6.0)
Requires-Dist: markdown (>=3,<4)
Requires-Dist: python-dateutil (>=2.8.0,<3.0.0)
Requires-Dist: python-slugify (>=5,<6)
Requires-Dist: tomli (>=2.0,<3.0)
Project-URL: Documentation, https://pages.goral.net.pl/stag/
Project-URL: Homepage, https://git.goral.net.pl/stag.git/about
Project-URL: Repository, https://git.goral.net.pl/stag.git
